lhagrid/__init__.py
lhagrid/_version.py
lhagrid/lhapdf.py
lhagrid/plot.py
lhagrid-0.0.3.dist-info/METADATA
lhagrid-0.0.3.dist-info/WHEEL
lhagrid-0.0.3.dist-info/licenses/LICENSE.txt
lhagrid-0.0.3.dist-info/RECORD
