Metadata-Version: 2.4
Name: lhagrid
Version: 0.0.3
Project-URL: Documentation, https://github.com/Alexander Puck Neuwirth/lhagrid#readme
Project-URL: Issues, https://github.com/Alexander Puck Neuwirth/lhagrid/issues
Project-URL: Source, https://github.com/Alexander Puck Neuwirth/lhagrid
Author-email: Alexander Puck Neuwirth <alexander@neuwirth-informatik.de>
License-File: LICENSE.txt
Classifier: Development Status :: 4 - Beta
Classifier: Programming Language :: Python
Classifier: Programming Language :: Python :: 3.8
Classifier: Programming Language :: Python :: 3.9
Classifier: Programming Language :: Python :: 3.10
Classifier: Programming Language :: Python :: 3.11
Classifier: Programming Language :: Python :: 3.12
Classifier: Programming Language :: Python :: Implementation :: CPython
Classifier: Programming Language :: Python :: Implementation :: PyPy
Requires-Python: >=3.8
Requires-Dist: pandas
